iputil/__init__.py
iputil/api.py
iputil/ip2region.py
iputil/xdbSearcher.py
iputil/data/ip2region.xdb
iputil-0.3.2.data/scripts/ip2region.py
iputil-0.3.2.dist-info/LICENSE.md
iputil-0.3.2.dist-info/METADATA
iputil-0.3.2.dist-info/WHEEL
iputil-0.3.2.dist-info/entry_points.txt
iputil-0.3.2.dist-info/top_level.txt
iputil-0.3.2.dist-info/RECORD
