Metadata-Version: 2.2
Name: iputil
Version: 0.3.2
Summary: Provide some useful util functions and a tool (ip2region) for ip processing
Author: Robin Lu
Classifier: Programming Language :: Python :: 3
Classifier: License :: OSI Approved :: Apache Software License
Classifier: Operating System :: OS Independent
Requires-Python: >=3.4.0
License-File: LICENSE.md
Dynamic: author
Dynamic: classifier
Dynamic: description
Dynamic: description-content-type
Dynamic: requires-python
Dynamic: summary
